odoo/addons/mail_activity_team/README.rst
odoo/addons/mail_activity_team/__init__.py
odoo/addons/mail_activity_team/__manifest__.py
odoo/addons/mail_activity_team/hooks.py
odoo/addons/mail_activity_team/patch.py
odoo/addons/mail_activity_team/i18n/es.po
odoo/addons/mail_activity_team/i18n/fr.po
odoo/addons/mail_activity_team/i18n/it.po
odoo/addons/mail_activity_team/i18n/mail_activity_team.pot
odoo/addons/mail_activity_team/migrations/18.0.1.0.0/post-migration.py
odoo/addons/mail_activity_team/models/__init__.py
odoo/addons/mail_activity_team/models/ir_actions_server.py
odoo/addons/mail_activity_team/models/mail_activity.py
odoo/addons/mail_activity_team/models/mail_activity_mixin.py
odoo/addons/mail_activity_team/models/mail_activity_team.py
odoo/addons/mail_activity_team/models/mail_activity_type.py
odoo/addons/mail_activity_team/models/res_users.py
odoo/addons/mail_activity_team/readme/CONTRIBUTORS.md
odoo/addons/mail_activity_team/readme/CREDITS.md
odoo/addons/mail_activity_team/readme/DESCRIPTION.md
odoo/addons/mail_activity_team/readme/USAGE.md
odoo/addons/mail_activity_team/security/ir.model.access.csv
odoo/addons/mail_activity_team/security/mail_activity_team_security.xml
odoo/addons/mail_activity_team/static/description/icon.png
odoo/addons/mail_activity_team/static/description/index.html
odoo/addons/mail_activity_team/static/src/components/activity_menu_view/activity_menu_view.xml
odoo/addons/mail_activity_team/static/src/core/web/activity.xml
odoo/addons/mail_activity_team/static/src/models/activity_menu.esm.js
odoo/addons/mail_activity_team/tests/__init__.py
odoo/addons/mail_activity_team/tests/test_mail_activity_team.py
odoo/addons/mail_activity_team/views/ir_actions_server_views.xml
odoo/addons/mail_activity_team/views/mail_activity_team_views.xml
odoo/addons/mail_activity_team/views/mail_activity_type.xml
odoo/addons/mail_activity_team/views/mail_activity_views.xml
odoo/addons/mail_activity_team/views/res_users_views.xml
odoo_addon_mail_activity_team-18.0.1.0.2.4.dist-info/METADATA
odoo_addon_mail_activity_team-18.0.1.0.2.4.dist-info/WHEEL
odoo_addon_mail_activity_team-18.0.1.0.2.4.dist-info/top_level.txt
odoo_addon_mail_activity_team-18.0.1.0.2.4.dist-info/RECORD
