Metadata-Version: 2.1
Name: odoo-addon-mail_activity_team
Version: 18.0.1.0.2.4
Requires-Python: >=3.10
Requires-Dist: odoo==18.0.*
Summary: Add Teams to Activities
Home-page: https://github.com/OCA/mail
License: AGPL-3
Author: ForgeFlow, Sodexis, Odoo Community Association (OCA)
Author-email: support@odoo-community.org
Classifier: Programming Language :: Python
Classifier: Framework :: Odoo
Classifier: Framework :: Odoo :: 18.0
Classifier: License :: OSI Approved :: GNU Affero General Public License v3
Classifier: Development Status :: 4 - Beta
